webspirit/__init__.py
webspirit/main.py
webspirit/addons/__init__.py
webspirit/addons/bookmarks.py
webspirit/application/__init__.py
webspirit/application/main.py
webspirit/application/server.py
webspirit/application/tray.py
webspirit/classes/__init__.py
webspirit/classes/webfiles.py
webspirit/classes/tools/__init__.py
webspirit/classes/tools/checktype.py
webspirit/classes/tools/contexterror.py
webspirit/classes/tools/csvmanager.py
webspirit/classes/tools/jsonmanager.py
webspirit/config/__init__.py
webspirit/config/constants.py
webspirit/config/dynamic_constants.py
webspirit/config/files_constants.py
webspirit/config/introspection.py
webspirit/config/logger.py
webspirit-0.0.3.dist-info/licenses/LICENSE.md
webspirit-0.0.3.dist-info/METADATA
webspirit-0.0.3.dist-info/WHEEL
webspirit-0.0.3.dist-info/entry_points.txt
webspirit-0.0.3.dist-info/top_level.txt
webspirit-0.0.3.dist-info/RECORD
