Metadata-Version: 2.4
Name: webspirit
Version: 0.0.3
Summary: A Python package for downloading resources from the web and organizing your bookmarks
Author-email: Solange <archange_paradise@proton.me>
License: MIT
Project-URL: Homepage, https://github.com/Archange-py/Webspirit/blob/main/README.md
Project-URL: Repository, https://github.com/Archange-py/Webspirit
Project-URL: Library, https://pypi.org/project/webspirit/
Project-URL: Documentation, https://archange-py.github.io/Webspirit
Keywords: webspirit,yt-dlp,POO,YouTube,download,bookmarks,collections,web-scrapping
Classifier: Programming Language :: Python :: 3
Classifier: License :: OSI Approved :: MIT License
Classifier: Operating System :: OS Independent
Requires-Python: >=3.12.4
License-File: LICENSE.md
Requires-Dist: pandas==2.3.0
Requires-Dist: colorlog==6.9.0
Requires-Dist: yt-dlp==2025.6.9
Requires-Dist: ipywidgets==8.1.7
Requires-Dist: beautifulsoup4==4.13.5
Requires-Dist: fastapi==0.127.1
Requires-Dist: uvicorn==0.40.0
Requires-Dist: pystray==0.19.5
Requires-Dist: pillow==12.0.0
Provides-Extra: dev
Requires-Dist: pytest; extra == "dev"
Dynamic: license-file
